{"description": "\n      \u041d\u0410\u041c \u041d\u0415 \u0421\u0422\u0420\u0410\u0428\u0415\u041d \u0421\u0415\u0420\u042b\u0419 \u0412\u041e\u041b\u041a!", "title": "\u0416\u0438\u043b-\u0431\u044b\u043b \u043d\u0430 \u0441\u0432\u0435\u0442\u0435 \u0441\u0435\u0440\u0435\u043d\u044c\u043a\u0438\u0439 \u043a\u043e\u0437\u043b\u0438\u043a", "duration": 1247, "ref": "http://www.mp3tales.info/audio/zhil_byl_na_svete_serenkij_kozlik.mp3", "id": "zhil-byl_na_svete_serenkij_kozlik", "thumb": "http://www.mp3tales.info/screen/pre/280x280xzhil_byl_na_svete_serenkij_kozlik.jpg.pagespeed.ic.vtUXPKCrgB.jpg"}